cubedpandas/__init__.py
cubedpandas/ambiguities.py
cubedpandas/common.py
cubedpandas/cube.py
cubedpandas/pandas_extension.py
cubedpandas/settings.py
cubedpandas/statistics.py
cubedpandas/context/__init__.py
cubedpandas/context/boolean_operation_context.py
cubedpandas/context/context.py
cubedpandas/context/context_context.py
cubedpandas/context/context_resolver.py
cubedpandas/context/cube_context.py
cubedpandas/context/datetime_resolver.py
cubedpandas/context/dimension_context.py
cubedpandas/context/enums.py
cubedpandas/context/expression.py
cubedpandas/context/filter_context.py
cubedpandas/context/function_context.py
cubedpandas/context/measure_context.py
cubedpandas/context/member_context.py
cubedpandas/context/member_not_found_context.py
cubedpandas/context/slice.py
cubedpandas/schema/dimension.py
cubedpandas/schema/dimension_collection.py
cubedpandas/schema/measure.py
cubedpandas/schema/measure_collection.py
cubedpandas/schema/member.py
cubedpandas/schema/schema.py
cubedpandas-0.2.37.dist-info/LICENSE
cubedpandas-0.2.37.dist-info/METADATA
cubedpandas-0.2.37.dist-info/WHEEL
cubedpandas-0.2.37.dist-info/top_level.txt
cubedpandas-0.2.37.dist-info/zip-safe
cubedpandas-0.2.37.dist-info/RECORD
