Metadata-Version: 2.1
Name: cubedpandas
Version: 0.2.37
Summary: Filter faster, analyze smarter – your DataFrames deserve it!
Home-page: https://github.com/Zeutschler/cubedpandas
Author: Thomas Zeutschler
Author-email: cubedpandas@gmail.com
Maintainer-email: CubedPandas Developers <cubedpandas@gmail.com>
License: MIT License
Project-URL: Homepage, https://zeutschler.github.io/cubedpandas/
Project-URL: Documentation, https://zeutschler.github.io/cubedpandas/
Project-URL: Repository, https://github.com/Zeutschler/cubedpandas.git
Project-URL: Issues, https://github.com/Zeutschler/cubedpandas/issues
Project-URL: Changelog, https://github.com/me/spam/blob/master/CHANGELOG.md
Project-URL: pypi, https://pypi.org/project/cubedpandas/
Keywords: pandas,analysis,database,olap,planning,reporting,forecasting,multidimensional,cube,data,dataframe,pivot,table
Platform: any
Classifier: Intended Audience :: Science/Research
Classifier: Intended Audience :: Developers
Classifier: License :: OSI Approved :: MIT License
Classifier: Development Status :: 3 - Alpha
Classifier: Programming Language :: Python :: 3.10
Classifier: Programming Language :: Python :: 3.11
Classifier: Programming Language :: Python :: 3.12
Classifier: Topic :: Software Development
Classifier: Topic :: Scientific/Engineering
Classifier: Operating System :: Microsoft :: Windows
Classifier: Operating System :: POSIX
Classifier: Operating System :: Unix
Classifier: Operating System :: MacOS
Requires-Python: >= 3.10
License-File: LICENSE
Requires-Dist: pandas
Requires-Dist: numpy
Requires-Dist: python-dateutil
Requires-Dist: datespan
